{
  "images": [
    { "image": "/images/contraste_mouvement/2401_dawn_drapé02014.jpg" },
    { "image": "/images/contraste_mouvement/home3.jpg" },
    { "image": "/images/contraste_mouvement/home4.jpg" },
    { "image": "/images/contraste_mouvement/home1.jpg" },
    { "image": "/images/reminescence/homeremi3.JPG" },
    { "image": "/images/reminescence/homeremi2.JPG" },
    { "image": "/images/reminescence/homeremi1.JPG" },
    { "image": "/images/collab/homecollab1.JPG" },
    { "image": "/images/collab/homecollab2.jpeg" },
    { "image": "/images/collab/homecollab3.jpeg" },
    { "image": "/images/reportage_meteore/look1-50.JPG" },
    { "image": "/images/placidite/homeremi2.JPG" },
    { "image": "/images/placidite/homepla1.JPG" },
    { "image": "/images/reportage_meteore/HOME1.JPG" },
    { "image": "/images/collab/homecollab4.JPG" }
  ]
}
